KamiStats/__init__.py
KamiStats/distributions.py
KamiStats/main.py
KamiStats-0.1.2.dist-info/LICENSE.txt
KamiStats-0.1.2.dist-info/METADATA
KamiStats-0.1.2.dist-info/WHEEL
KamiStats-0.1.2.dist-info/entry_points.txt
KamiStats-0.1.2.dist-info/top_level.txt
KamiStats-0.1.2.dist-info/RECORD
