Metadata-Version: 2.1
Name: KamiStats
Version: 0.1.2
Summary: A statistics library project
Author-email: Kishimita <kishimita7@gmail.com>
License: MIT
Project-URL: Homepage, https://www.github.com/kishimita/kamistats
Project-URL: Issues, https://www.github.com/kishimita/kamistats/issues
Keywords: statistics distributions,probability,random variables,pdf,cdf,mean,variance,ßstandard deviation
Classifier: Development Status :: 5 - Production/Stable
Classifier: Programming Language :: Python :: 3
Classifier: License :: OSI Approved :: MIT License
Classifier: Operating System :: OS Independent
Requires-Python: >=3.9
License-File: LICENSE.txt
Requires-Dist: scipy >=1.13.0
Requires-Dist: sympy >=1.13.0
